{
  "books": [
    {
      "id": "/works/OL27903945W",
      "title": "Summary of the 48 Laws of Power by Robert Greene",
      "author": "Podium PRESS",
      "image": "https://covers.openlibrary.org/b/id/14911145-L.jpg",
      "status": "Want to Read"
    },
    {
      "id": "/works/OL34756485W",
      "title": "Las 48 leyes del poder",
      "author": "Robert Greene",
      "image": "https://covers.openlibrary.org/b/id/13482302-L.jpg",
      "status": "Want to Read",
      "dateAdded": "2026-05-15"
    }
  ]
}